django_chart_compare/__init__.py
django_chart_compare/charters.py
django_chart_compare-1.0.4.dist-info/LICENSE
django_chart_compare-1.0.4.dist-info/METADATA
django_chart_compare-1.0.4.dist-info/WHEEL
django_chart_compare-1.0.4.dist-info/top_level.txt
django_chart_compare-1.0.4.dist-info/RECORD
